{
  "questionId": "2005",
  "titleSlug": "check-if-all-the-integers-in-a-range-are-covered",
  "title": "Check if All the Integers in a Range Are Covered",
  "exampleTestcases": "[[1,2],[3,4],[5,6]]\n2\n5\n[[1,10],[10,20]]\n21\n21",
  "sampleTestCase": "[[1,2],[3,4],[5,6]]\n2\n5",
  "metaData": "{\n  \"name\": \"isCovered\",\n  \"params\": [\n    {\n      \"name\": \"ranges\",\n      \"type\": \"integer[][]\"\n    },\n    {\n      \"type\": \"integer\",\n      \"name\": \"left\"\n    },\n    {\n      \"type\": \"integer\",\n      \"name\": \"right\"\n    }\n  ],\n  \"return\": {\n    \"type\": \"boolean\"\n  }\n}"
}