{
  "questionId": "1743",
  "titleSlug": "count-substrings-that-differ-by-one-character",
  "title": "Count Substrings That Differ by One Character",
  "exampleTestcases": "\"aba\"\n\"baba\"\n\"ab\"\n\"bb\"",
  "sampleTestCase": "\"aba\"\n\"baba\"",
  "metaData": "{\n  \"name\": \"countSubstrings\",\n  \"params\": [\n    {\n      \"name\": \"s\",\n      \"type\": \"string\"\n    },\n    {\n      \"type\": \"string\",\n      \"name\": \"t\"\n    }\n  ],\n  \"return\": {\n    \"type\": \"integer\"\n  }\n}"
}