{
  "questionId": "2200",
  "titleSlug": "stamping-the-grid",
  "title": "Stamping the Grid",
  "exampleTestcases": "[[1,0,0,0],[1,0,0,0],[1,0,0,0],[1,0,0,0],[1,0,0,0]]\n4\n3\n[[1,0,0,0],[0,1,0,0],[0,0,1,0],[0,0,0,1]]\n2\n2",
  "sampleTestCase": "[[1,0,0,0],[1,0,0,0],[1,0,0,0],[1,0,0,0],[1,0,0,0]]\n4\n3",
  "metaData": "{\n  \"name\": \"possibleToStamp\",\n  \"params\": [\n    {\n      \"name\": \"grid\",\n      \"type\": \"integer[][]\"\n    },\n    {\n      \"type\": \"integer\",\n      \"name\": \"stampHeight\"\n    },\n    {\n      \"type\": \"integer\",\n      \"name\": \"stampWidth\"\n    }\n  ],\n  \"return\": {\n    \"type\": \"boolean\"\n  }\n}"
}