{
  "questionId": "595",
  "titleSlug": "big-countries",
  "title": "Big Countries",
  "exampleTestcases": "{\"headers\": {\"World\": [\"name\", \"continent\",\t\"area\",\t\"population\", \"gdp\"]}, \"rows\": {\"World\": [[\"Afghanistan\", \"Asia\", 652230, 25500100, 20343000000], [\"Albania\", \"Europe\", 28748, 2831741, 12960000000], [\"Algeria\", \"Africa\", 2381741, 37100000, 188681000000], [\"Andorra\", \"Europe\", 468, 78115,\t3712000000], [\"Angola\", \"Africa\", 1246700, 20609294, 100990000000]]}}",
  "sampleTestCase": "{\"headers\": {\"World\": [\"name\", \"continent\",\t\"area\",\t\"population\", \"gdp\"]}, \"rows\": {\"World\": [[\"Afghanistan\", \"Asia\", 652230, 25500100, 20343000000], [\"Albania\", \"Europe\", 28748, 2831741, 12960000000], [\"Algeria\", \"Africa\", 2381741, 37100000, 188681000000], [\"Andorra\", \"Europe\", 468, 78115,\t3712000000], [\"Angola\", \"Africa\", 1246700, 20609294, 100990000000]]}}",
  "metaData": "{\"mysql\": [\"Create table If Not Exists World (name varchar(255), continent varchar(255), area int, population int, gdp bigint)\"], \"mssql\": [\"Create table World (name varchar(255), continent varchar(255), area int, population int, gdp bigint)\"], \"oraclesql\": [\"Create table World (name varchar(255), continent varchar(255), area int, population int, gdp int)\"], \"database\": true, \"name\": \"big_countries\", \"pythondata\": [\"World = pd.DataFrame([], columns=['name', 'continent', 'area', 'population', 'gdp']).astype({'name':'object', 'continent':'object', 'area':'Int64', 'population':'Int64', 'gdp':'Int64'})\"], \"manual\": false, \"postgresql\": [\"Create table If Not Exists World (name varchar(255), continent varchar(255), area int, population int, gdp bigint)\"], \"database_schema\": {\"World\": {\"name\": \"VARCHAR(255)\", \"continent\": \"VARCHAR(255)\", \"area\": \"INT\", \"population\": \"INT\", \"gdp\": \"BIGINT\"}}}"
}